fix_future_annotations/__init__.py
fix_future_annotations/_config.py
fix_future_annotations/_main.py
fix_future_annotations/_utils.py
fix_future_annotations/_visitor.py
fix_future_annotations-0.5.0.dist-info/entry_points.txt
fix_future_annotations-0.5.0.dist-info/WHEEL
fix_future_annotations-0.5.0.dist-info/METADATA
fix_future_annotations-0.5.0.dist-info/licenses/LICENSE
fix_future_annotations-0.5.0.dist-info/RECORD
