Metadata-Version: 2.1
Name: fix-future-annotations
Version: 0.5.0
Summary: A CLI and pre-commit hook to upgrade the typing annotations syntax to PEP 585 and PEP 604
License: MIT
Author-email: Frost Ming <me@frostming.com>
Requires-Python: >=3.8
Requires-Dist: tokenize-rt>=5.0.0
Requires-Dist: tomli; python_version < "3.11"
Project-URL: Homepage, https://github.com/frostming/fix-future-annotations
Project-URL: Releases, https://github.com/frostming/fix-future-annotations/releases
